nox_actions/__init__.py
nox_actions/codetest.py
nox_actions/lint.py
nox_actions/release.py
nox_actions/utils.py
tests/__init__.py
tests/conftest.py
tests/test_imports.py
tests/test_server.py
tests/data/yaml/entity_schema.yaml
tests/data/yaml/schema.yaml
orange_shotgrid_mcp_server-0.2.5.dist-info/METADATA
orange_shotgrid_mcp_server-0.2.5.dist-info/WHEEL
orange_shotgrid_mcp_server-0.2.5.dist-info/entry_points.txt
orange_shotgrid_mcp_server-0.2.5.dist-info/licenses/LICENSE
orange_shotgrid_mcp_server-0.2.5.dist-info/RECORD
